<?xml version="1.0" encoding="UTF-8"?>
<!DOCTYPE mapper PUBLIC "-//mybatis.org//DTD Mapper 3.0//EN" "http://mybatis.org/dtd/mybatis-3-mapper.dtd">
<mapper namespace="com.cduestc.keep.mapper.KeepLessonExMapper">
    <resultMap id="BaseResultMap" type="com.cduestc.keep.model.KeepLesson">
        <!--
          WARNING - @mbg.generated
          This element is automatically generated by MyBatis Generator, do not modify.
          This element was generated on Tue Apr 14 18:36:48 CST 2020.
        -->
        <id column="id" jdbcType="BIGINT" property="id" />
        <result column="lesson_name" jdbcType="VARCHAR" property="lessonName" />
        <result column="image_url" jdbcType="VARCHAR" property="imageUrl" />
        <result column="sports" jdbcType="VARCHAR" property="sports" />
        <result column="hot" jdbcType="INTEGER" property="hot" />
        <result column="type" jdbcType="VARCHAR" property="type" />
        <result column="time" jdbcType="INTEGER" property="time" />
        <result column="calorie" jdbcType="INTEGER" property="calorie" />
        <result column="resource_url" jdbcType="VARCHAR" property="resourceUrl" />
    </resultMap>
    <select id="getHotLesson" resultType="com.cduestc.keep.model.KeepLesson">
        select * from keep_lesson order by hot desc
    </select>
    <update id="updateHot" >
        update keep_lesson set hot=hot+#{i} where id=#{id}
    </update>
</mapper>